{
  "nextId": [
    {
      "id": "1",
      "testId": 6
    }
  ],
  "customers": [
    {
      "id": "7434300988",
      "name": "Nurəli"
    }
  ],
  "orders": [
    {
      "id": "1",
      "customerId": "7434300988",
      "orderNumber": "72",
      "status": "Gozleyir",
      "date": "2024-11-14"
    },
    {
      "id": "2",
      "customerId": "7434300988",
      "orderNumber": "62",
      "status": "Gozleyir",
      "date": "2024-11-14"
    },
    {
      "id": "3",
      "customerId": "7434300988",
      "orderNumber": "62",
      "status": "Gozleyir",
      "date": "2024-11-14"
    },
    {
      "id": "4",
      "customerId": "7434300988",
      "orderNumber": "62",
      "status": "Gozleyir",
      "date": "2024-11-14"
    },
    {
      "id": "5",
      "customerId": "7434300988",
      "orderNumber": "72",
      "status": "Gozleyir",
      "date": "2024-11-14"
    },
    {
      "id": "6",
      "customerId": "7434300988",
      "orderNumber": "73",
      "status": "Gozleyir",
      "date": "2024-11-14"
    }
  ]
}